ez_zarr/__init__.py
ez_zarr/__main__.py
ez_zarr/hcs_wrappers.py
ez_zarr/ome_zarr.py
ez_zarr/plotting.py
ez_zarr/utils.py
ez_zarr-0.4.2.dist-info/licenses/LICENSE
ez_zarr-0.4.2.dist-info/METADATA
ez_zarr-0.4.2.dist-info/WHEEL
ez_zarr-0.4.2.dist-info/entry_points.txt
ez_zarr-0.4.2.dist-info/top_level.txt
ez_zarr-0.4.2.dist-info/RECORD
