Metadata-Version: 2.4
Name: ez_zarr
Version: 0.4.2
Summary: Give easy, high-level access to ome-zarr filesets.
Author: Silvia Barbiero, Charlotte Soneson, Michael Stadler
Maintainer-email: Michael Stadler <michael.stadler@fmi.ch>
License-Expression: MIT
Project-URL: Homepage, https://github.com/fmicompbio/ez_zarr
Project-URL: Issues, https://github.com/fmicompbio/ez_zarr/issues
Project-URL: Documentation, https://fmicompbio.github.io/ez_zarr/
Project-URL: Sources, https://github.com/fmicompbio/ez_zarr
Keywords: ome_zarr,image analysis,Fractal
Classifier: Development Status :: 3 - Alpha
Classifier: Intended Audience :: Science/Research
Classifier: Operating System :: OS Independent
Classifier: Programming Language :: Python
Classifier: Programming Language :: Python :: 3
Classifier: Programming Language :: Python :: 3 :: Only
Classifier: Programming Language :: Python :: 3.11
Classifier: Programming Language :: Python :: 3.12
Classifier: Programming Language :: Python :: 3.13
Requires-Python: >=3.11
License-File: LICENSE
Requires-Dist: anndata
Requires-Dist: dask
Requires-Dist: numpy
Requires-Dist: pandas
Requires-Dist: zarr>=3.0.0a0
Requires-Dist: matplotlib
Requires-Dist: scikit-image
Requires-Dist: rich
Provides-Extra: dev
Requires-Dist: pytest; extra == "dev"
Requires-Dist: pytest-cov; extra == "dev"
Provides-Extra: doc
Requires-Dist: requests; extra == "doc"
Requires-Dist: session-info; extra == "doc"
Dynamic: license-file
